{"version":3,"kind":"Notebook","sha256":"0bd2c7a890d8a69ee1bdddfb9f410334f30143d2ef3eb22f1403c48aa0bec049","slug":"overview","location":"/basics/overview.ipynb","dependencies":[],"frontmatter":{"title":"Overview","content_includes_title":false,"kernelspec":{"name":"cs171","display_name":"cs171","language":"python"},"authors":[{"id":"Mike Wood","name":"Mike Wood"}],"github":"https://github.com/ProfMikeWood/machine_learning_book","keywords":["machine learning","data science","AI","marine science","climate science"],"numbering":{"title":{"offset":1}},"source_url":"https://github.com/ProfMikeWood/machine_learning_book/blob/main/basics/overview.ipynb","edit_url":"https://github.com/ProfMikeWood/machine_learning_book/edit/main/basics/overview.ipynb","thumbnail":"/Mauna_Loa_Observator-be214837ca82d3893d4c888684970bd6.jpg","thumbnailOptimized":"/Mauna_Loa_Observator-be214837ca82d3893d4c888684970bd6.webp","exports":[{"format":"ipynb","filename":"overview.ipynb","url":"/overview-cd159a0d789e09a32c3aa55262e83d01.ipynb"}]},"widgets":{},"mdast":{"type":"root","children":[{"type":"block","kind":"notebook-content","children":[{"type":"paragraph","position":{"start":{"line":1,"column":1},"end":{"line":1,"column":1}},"children":[{"type":"strong","position":{"start":{"line":1,"column":1},"end":{"line":1,"column":1}},"children":[{"type":"text","value":"Motivation","position":{"start":{"line":1,"column":1},"end":{"line":1,"column":1}},"key":"GHBzzYspUN"}],"key":"IJs1djFsJR"}],"key":"Xaq1RuwJE2"},{"type":"paragraph","position":{"start":{"line":3,"column":1},"end":{"line":3,"column":1}},"children":[{"type":"text","value":"Machine learning is a popular topic these days, but in reality, it has been a topic of study for quite some time as a subset of data science. As a transition to thinking about machine learning approaches and algorithms, it’s helpful to consider a simple example common to data analysis - linear regression. In the subsequent subsections under Machine Learning Basics, we’ll use a set of linear regression examples to introduce machine learning terminology and a common framework that will apply to other algorithms and applications down the road. In this notebook, we’ll take a look at our example data - CO","position":{"start":{"line":3,"column":1},"end":{"line":3,"column":1}},"key":"BOoQ8ghm0j"},{"type":"inlineMath","value":"_2","position":{"start":{"line":3,"column":1},"end":{"line":3,"column":1}},"html":"<span class=\"katex\"><span class=\"katex-mathml\"><math xmlns=\"http://www.w3.org/1998/Math/MathML\"><semantics><mrow><msub><mrow></mrow><mn>2</mn></msub></mrow><annotation encoding=\"application/x-tex\">_2</annotation></semantics></math></span><span class=\"katex-html\" aria-hidden=\"true\"><span class=\"base\"><span class=\"strut\" style=\"height:0.4511em;vertical-align:-0.15em;\"></span><span class=\"mord\"><span></span><span class=\"msupsub\"><span class=\"vlist-t vlist-t2\"><span class=\"vlist-r\"><span class=\"vlist\" style=\"height:0.3011em;\"><span style=\"top:-2.55em;margin-right:0.05em;\"><span class=\"pstrut\" style=\"height:2.7em;\"></span><span class=\"sizing reset-size6 size3 mtight\"><span class=\"mord mtight\">2</span></span></span></span><span class=\"vlist-s\">​</span></span><span class=\"vlist-r\"><span class=\"vlist\" style=\"height:0.15em;\"><span></span></span></span></span></span></span></span></span></span>","key":"d1ulYWVkQj"},{"type":"text","value":" concentrations collected at the Mauna Loa Observatory a.k.a. the “Keeling Curve”.","position":{"start":{"line":3,"column":1},"end":{"line":3,"column":1}},"key":"IYgBtJwKfN"}],"key":"fokcpVNKL1"},{"type":"paragraph","position":{"start":{"line":6,"column":1},"end":{"line":6,"column":1}},"children":[{"type":"strong","position":{"start":{"line":6,"column":1},"end":{"line":6,"column":1}},"children":[{"type":"text","value":"Import modules","position":{"start":{"line":6,"column":1},"end":{"line":6,"column":1}},"key":"Y5MNgc3m2U"}],"key":"whx4bu7jcp"}],"key":"N7Zb0IqSRP"},{"type":"paragraph","position":{"start":{"line":8,"column":1},"end":{"line":8,"column":1}},"children":[{"type":"text","value":"Begin by importing the modules to be used in this notebook:","position":{"start":{"line":8,"column":1},"end":{"line":8,"column":1}},"key":"L8p5MnWef3"}],"key":"KfrC6J281k"}],"key":"T6dKp3XkDK"},{"type":"block","kind":"notebook-code","children":[{"type":"code","lang":"python","executable":true,"value":"import numpy as np\nimport matplotlib.pyplot as plt\nimport pandas as pd","key":"DqWywIUwLL"},{"type":"outputs","id":"hJXxYQiiub3U9AWLXcPXv","children":[],"key":"UWisfwXsRg"}],"key":"egFXnDrSsu"},{"type":"block","kind":"notebook-content","children":[{"type":"heading","depth":2,"position":{"start":{"line":1,"column":1},"end":{"line":1,"column":1}},"children":[{"type":"text","value":"Mauna Loa CO","position":{"start":{"line":1,"column":1},"end":{"line":1,"column":1}},"key":"yS64lrnIP3"},{"type":"inlineMath","value":"_2","position":{"start":{"line":1,"column":1},"end":{"line":1,"column":1}},"html":"<span class=\"katex\"><span class=\"katex-mathml\"><math xmlns=\"http://www.w3.org/1998/Math/MathML\"><semantics><mrow><msub><mrow></mrow><mn>2</mn></msub></mrow><annotation encoding=\"application/x-tex\">_2</annotation></semantics></math></span><span class=\"katex-html\" aria-hidden=\"true\"><span class=\"base\"><span class=\"strut\" style=\"height:0.4511em;vertical-align:-0.15em;\"></span><span class=\"mord\"><span></span><span class=\"msupsub\"><span class=\"vlist-t vlist-t2\"><span class=\"vlist-r\"><span class=\"vlist\" style=\"height:0.3011em;\"><span style=\"top:-2.55em;margin-right:0.05em;\"><span class=\"pstrut\" style=\"height:2.7em;\"></span><span class=\"sizing reset-size6 size3 mtight\"><span class=\"mord mtight\">2</span></span></span></span><span class=\"vlist-s\">​</span></span><span class=\"vlist-r\"><span class=\"vlist\" style=\"height:0.15em;\"><span></span></span></span></span></span></span></span></span></span>","key":"RVCYPYw7ts"},{"type":"text","value":" Measurements","position":{"start":{"line":1,"column":1},"end":{"line":1,"column":1}},"key":"ZjDlZ959FG"}],"identifier":"mauna-loa-co-2-measurements","label":"Mauna Loa CO_2 Measurements","html_id":"mauna-loa-co-2-measurements","implicit":true,"key":"h900TArbMU"},{"type":"paragraph","position":{"start":{"line":3,"column":1},"end":{"line":3,"column":1}},"children":[{"type":"text","value":"For a concrete example, we will consider the trend in CO","position":{"start":{"line":3,"column":1},"end":{"line":3,"column":1}},"key":"MSoJOmlzrc"},{"type":"inlineMath","value":"_2","position":{"start":{"line":3,"column":1},"end":{"line":3,"column":1}},"html":"<span class=\"katex\"><span class=\"katex-mathml\"><math xmlns=\"http://www.w3.org/1998/Math/MathML\"><semantics><mrow><msub><mrow></mrow><mn>2</mn></msub></mrow><annotation encoding=\"application/x-tex\">_2</annotation></semantics></math></span><span class=\"katex-html\" aria-hidden=\"true\"><span class=\"base\"><span class=\"strut\" style=\"height:0.4511em;vertical-align:-0.15em;\"></span><span class=\"mord\"><span></span><span class=\"msupsub\"><span class=\"vlist-t vlist-t2\"><span class=\"vlist-r\"><span class=\"vlist\" style=\"height:0.3011em;\"><span style=\"top:-2.55em;margin-right:0.05em;\"><span class=\"pstrut\" style=\"height:2.7em;\"></span><span class=\"sizing reset-size6 size3 mtight\"><span class=\"mord mtight\">2</span></span></span></span><span class=\"vlist-s\">​</span></span><span class=\"vlist-r\"><span class=\"vlist\" style=\"height:0.15em;\"><span></span></span></span></span></span></span></span></span></span>","key":"oFQWplDyBD"},{"type":"text","value":" concentration in the atmosphere as measured at the Mauna Loa Observatory on the Mauna Loa volcano in Hilo Hawaii:","position":{"start":{"line":3,"column":1},"end":{"line":3,"column":1}},"key":"EfaW2r50fx"}],"key":"f4rk31tCk9"}],"key":"H2I3ogflM4"},{"type":"block","kind":"notebook-content","children":[{"type":"image","url":"/Mauna_Loa_Observator-be214837ca82d3893d4c888684970bd6.jpg","alt":"Mauna Loa Observatory","width":"500px","align":"center","key":"exxVzKh3uy","urlSource":"../images/Mauna_Loa_Observatory.jpg","urlOptimized":"/Mauna_Loa_Observator-be214837ca82d3893d4c888684970bd6.webp"}],"key":"CUBvNKH4LP"},{"type":"block","kind":"notebook-content","children":[{"type":"paragraph","position":{"start":{"line":1,"column":1},"end":{"line":1,"column":1}},"children":[{"type":"text","value":"Photo Credit: Johnathon Kingston, ","position":{"start":{"line":1,"column":1},"end":{"line":1,"column":1}},"key":"KaI0hdrE3d"},{"type":"link","url":"https://education.nationalgeographic.org/resource/mauna-loa-observatory/","position":{"start":{"line":1,"column":1},"end":{"line":1,"column":1}},"children":[{"type":"text","value":"National Geographic","position":{"start":{"line":1,"column":1},"end":{"line":1,"column":1}},"key":"iYXrXIjX2L"}],"urlSource":"https://education.nationalgeographic.org/resource/mauna-loa-observatory/","key":"wIMNUvQfmE"},{"type":"text","value":".","position":{"start":{"line":1,"column":1},"end":{"line":1,"column":1}},"key":"JEusAnA78X"}],"key":"gvEEsoNGXI"},{"type":"paragraph","position":{"start":{"line":4,"column":1},"end":{"line":4,"column":1}},"children":[{"type":"text","value":"The record of CO","position":{"start":{"line":4,"column":1},"end":{"line":4,"column":1}},"key":"hbh7orxxdB"},{"type":"inlineMath","value":"_2","position":{"start":{"line":4,"column":1},"end":{"line":4,"column":1}},"html":"<span class=\"katex\"><span class=\"katex-mathml\"><math xmlns=\"http://www.w3.org/1998/Math/MathML\"><semantics><mrow><msub><mrow></mrow><mn>2</mn></msub></mrow><annotation encoding=\"application/x-tex\">_2</annotation></semantics></math></span><span class=\"katex-html\" aria-hidden=\"true\"><span class=\"base\"><span class=\"strut\" style=\"height:0.4511em;vertical-align:-0.15em;\"></span><span class=\"mord\"><span></span><span class=\"msupsub\"><span class=\"vlist-t vlist-t2\"><span class=\"vlist-r\"><span class=\"vlist\" style=\"height:0.3011em;\"><span style=\"top:-2.55em;margin-right:0.05em;\"><span class=\"pstrut\" style=\"height:2.7em;\"></span><span class=\"sizing reset-size6 size3 mtight\"><span class=\"mord mtight\">2</span></span></span></span><span class=\"vlist-s\">​</span></span><span class=\"vlist-r\"><span class=\"vlist\" style=\"height:0.15em;\"><span></span></span></span></span></span></span></span></span></span>","key":"Dvx9Lrhwt4"},{"type":"text","value":" concentrations collected at Mauna Loa, sometimes referred to as the “Keeling Curve” for its founding scientist, is a multi-decadal record that is available from the Scripps Institute of Oceanography ","position":{"start":{"line":4,"column":1},"end":{"line":4,"column":1}},"key":"oBwT2Xixfm"},{"type":"link","url":"https://keelingcurve.ucsd.edu/","position":{"start":{"line":4,"column":1},"end":{"line":4,"column":1}},"children":[{"type":"text","value":"HERE","position":{"start":{"line":4,"column":1},"end":{"line":4,"column":1}},"key":"Tt04ltcK1o"}],"urlSource":"https://keelingcurve.ucsd.edu/","key":"Ko5OXJ9fKw"},{"type":"text","value":". The video ","position":{"start":{"line":4,"column":1},"end":{"line":4,"column":1}},"key":"pqiZuHsBSK"},{"type":"link","url":"https://youtu.be/dXBzFNEwoj8","position":{"start":{"line":4,"column":1},"end":{"line":4,"column":1}},"children":[{"type":"text","value":"HERE","position":{"start":{"line":4,"column":1},"end":{"line":4,"column":1}},"key":"fxnxrCpNRZ"}],"urlSource":"https://youtu.be/dXBzFNEwoj8","key":"IAgD10mVcY"},{"type":"text","value":" for information on how the data is collected.","position":{"start":{"line":4,"column":1},"end":{"line":4,"column":1}},"key":"AHK29b6EcE"}],"key":"J3i6dms31O"},{"type":"paragraph","position":{"start":{"line":6,"column":1},"end":{"line":6,"column":1}},"children":[{"type":"text","value":"Here, we will work the monthly data in this dataset, which is available in the ","position":{"start":{"line":6,"column":1},"end":{"line":6,"column":1}},"key":"Md3SYfvlwG"},{"type":"inlineCode","value":"monthly_in_situ_co2_mlo.csv","position":{"start":{"line":6,"column":1},"end":{"line":6,"column":1}},"key":"nOgJ0BslTy"},{"type":"text","value":" file provided in the data directory of this book. Let’s read that in here:","position":{"start":{"line":6,"column":1},"end":{"line":6,"column":1}},"key":"usupJNmBxy"}],"key":"DcMXKm9Ws9"}],"key":"qHoUcmEu6u"},{"type":"block","kind":"notebook-code","children":[{"type":"code","lang":"python","executable":true,"value":"# read in the dataset with pandas\ndf = pd.read_csv('../data/monthly_in_situ_co2_mlo.csv', skiprows=64)\n\n# filter out null values stored as -99\ndf = df[df.iloc[:, 4] >0]\n\n# the decimal year information is in the 4th column\nx = df.iloc[:, 3]\n\n# the CO2 information is in the 5th column\ny = df.iloc[:, 4]","key":"FIVHotPoyl"},{"type":"outputs","id":"8hSWMQZj_bielsxtnF5lv","children":[],"key":"VjgMCILRNs"}],"key":"tuvf6J99Yx"},{"type":"block","kind":"notebook-content","children":[{"type":"paragraph","position":{"start":{"line":1,"column":1},"end":{"line":1,"column":1}},"children":[{"type":"text","value":"Let’s take a look at what this data looks like:","position":{"start":{"line":1,"column":1},"end":{"line":1,"column":1}},"key":"GeqNICgD8A"}],"key":"XsaHNt2wql"}],"key":"K8A3cd0Jai"},{"type":"block","kind":"notebook-code","children":[{"type":"code","lang":"python","executable":true,"value":"plt.figure(figsize=(8,4))\nplt.plot(x,y,'k.')\nplt.xlabel('x (year)')\nplt.ylabel('y (CO$_2$ concentration, ppm)')\nplt.show()","key":"tCtfqzOsn5"},{"type":"outputs","id":"zXtsm-QV44yjSxrfTQN6h","children":[{"type":"output","jupyter_data":{"output_type":"display_data","metadata":{},"data":{"image/png":{"content_type":"image/png","hash":"8da0594fe9d55401035a0b2a0cdadba1","path":"/8da0594fe9d55401035a0b2a0cdadba1.png"},"text/plain":{"content":"<Figure size 800x400 with 1 Axes>","content_type":"text/plain"}}},"children":[],"key":"SsvNTBUhK3"}],"key":"C1Up6v4Cmw"}],"key":"M03VvEtESN"},{"type":"block","kind":"notebook-content","children":[{"type":"paragraph","position":{"start":{"line":1,"column":1},"end":{"line":1,"column":1}},"children":[{"type":"text","value":"As we can see, this record extends back to the 1950’s and continues through present day. We’ll take a number of approaches to investigate this data in the next notebooks.","position":{"start":{"line":1,"column":1},"end":{"line":1,"column":1}},"key":"Cczjveb5Y7"}],"key":"NRyAYCoyZB"}],"key":"gwRaDOzfkg"}],"key":"ludJQKnyUN"},"references":{"cite":{"order":[],"data":{}}}}